jupyddl/__init__.py
jupyddl/a_star.py
jupyddl/automated_planner.py
jupyddl/bfs.py
jupyddl/data_analyst.py
jupyddl/dfs.py
jupyddl/dijkstra.py
jupyddl/greedy_best_first.py
jupyddl/heuristics.py
jupyddl/metrics.py
jupyddl/node.py
jupyddl-0.4.1.dist-info/LICENSE
jupyddl-0.4.1.dist-info/METADATA
jupyddl-0.4.1.dist-info/WHEEL
jupyddl-0.4.1.dist-info/top_level.txt
jupyddl-0.4.1.dist-info/RECORD
