Metadata-Version: 2.1
Name: jupyddl
Version: 0.4.1
Summary: Jupyddl is a PDDL planner built on top of a Julia parser
Home-page: https://github.com/apla-toolbox/pythonpddl
Author: Erwin Lejeune
Author-email: erwinlejeune.pro@gmail.com
License: UNKNOWN
Platform: UNKNOWN
Classifier: Programming Language :: Python :: 3 :: Only
Classifier: Programming Language :: Python :: 3.6
Classifier: Programming Language :: Python :: 3.7
Classifier: Programming Language :: Python :: 3.8
Classifier: Programming Language :: Python :: 3
Classifier: License :: OSI Approved :: Apache Software License
Classifier: Operating System :: Unix
Classifier: Operating System :: MacOS
Classifier: Framework :: Pytest
Requires-Python: >=3.6
Requires-Dist: julia (==0.5.6)
Requires-Dist: coloredlogs (==15.0)
Requires-Dist: matplotlib (==3.3.3)
